<?xml version="1.0" encoding="UTF-8"?>
<Defs>
  <!-- GenericKitchen -->
  <KCSG.StructureLayoutDef>
    <defName>VFESKitchenFreezerSmallDining</defName>
    <layouts>
      <li>
        <li>.,.,.,.,.,.,.,.</li>
        <li>.,.,.,MealLavish,MealFine,MealNutrientPaste,MealLavish,.</li>
        <li>.,.,.,MealLavish,.,.,MealSimple,.</li>
        <li>.,.,.,.,.,.,.,.</li>
        <li>.,.,.,.,.,.,.,.</li>
        <li>.,.,.,.,.,.,.,.</li>
        <li>.,.,.,.,.,.,.,.</li>
        <li>.,.,.,.,.,.,.,.</li>
      </li>
      <li>
        <li>.,.,MetalTile,MetalTile,MetalTile,MetalTile,MetalTile,MetalTile</li>
        <li>.,.,MetalTile,MetalTile,MetalTile,MetalTile,MetalTile,MetalTile</li>
        <li>.,.,MetalTile,MetalTile,MetalTile,MetalTile,MetalTile,MetalTile</li>
        <li>MetalTile,MetalTile,MetalTile,MetalTile,MetalTile,MetalTile,MetalTile,MetalTile</li>
        <li>MetalTile,MetalTile,MetalTile,MetalTile,MetalTile,MetalTile,MetalTile,MetalTile</li>
        <li>MetalTile,MetalTile,MetalTile,MetalTile,MetalTile,MetalTile,MetalTile,MetalTile</li>
        <li>MetalTile,MetalTile,MetalTile,MetalTile,MetalTile,MetalTile,MetalTile,MetalTile</li>
        <li>MetalTile,MetalTile,MetalTile,MetalTile,MetalTile,MetalTile,MetalTile,MetalTile</li>
      </li>
      <li>
        <li>.,.,Wall_BlocksGranite,Wall_BlocksGranite,Cooler_South,Wall_BlocksGranite,Wall_BlocksGranite,Wall_BlocksGranite</li>
        <li>Stool_Steel_North,Stool_Steel_North,Wall_BlocksGranite,.,Shelf_WoodLog_North,.,Shelf_WoodLog_West,Wall_BlocksGranite</li>
        <li>Table1x2c_Steel_East,.,Wall_BlocksGranite,Shelf_WoodLog_East,.,.,.,Wall_BlocksGranite</li>
        <li>Wall_BlocksGranite,Wall_BlocksGranite,Wall_BlocksGranite,Wall_BlocksGranite,Wall_BlocksGranite,.,.,Wall_BlocksGranite</li>
        <li>Wall_BlocksGranite,.,ElectricStove_South,.,Wall_BlocksGranite,Door_Steel,Wall_BlocksGranite,Wall_BlocksGranite</li>
        <li>Door_Steel,.,Stool_Steel_North,.,StandingLamp,.,.,Wall_BlocksGranite</li>
        <li>Wall_BlocksGranite,.,.,.,.,.,.,Wall_BlocksGranite</li>
        <li>Wall_BlocksGranite,Wall_BlocksGranite,Wall_BlocksGranite,Wall_BlocksGranite,Wall_BlocksGranite,Wall_BlocksGranite,Wall_BlocksGranite,Wall_BlocksGranite</li>
      </li>
    </layouts>
    <roofGrid>
      <li>.,.,1,1,1,1,1,1</li>
      <li>1,1,1,1,1,1,1,1</li>
      <li>1,1,1,1,1,1,1,1</li>
      <li>1,1,1,1,1,1,1,1</li>
      <li>1,1,1,1,1,1,1,1</li>
      <li>1,1,1,1,1,1,1,1</li>
      <li>1,1,1,1,1,1,1,1</li>
      <li>1,1,1,1,1,1,1,1</li>
    </roofGrid>
    <tags>
      <li>GenericKitchen</li>
    </tags>
  </KCSG.StructureLayoutDef>
  <KCSG.StructureLayoutDef>
    <defName>VFESKitchenDining</defName>
    <layouts>
      <li>
        <li>.,.,.,.,.,.,.,.,.,.</li>
        <li>.,.,.,.,.,.,.,.,.,.</li>
        <li>.,.,.,.,MealFine,MealFine,.,MealFine,.,.</li>
        <li>.,.,.,.,.,.,.,.,.,.</li>
        <li>.,.,.,.,.,.,.,.,.,.</li>
        <li>.,.,.,.,.,.,.,.,.,.</li>
        <li>.,.,.,.,.,.,.,.,.,.</li>
        <li>.,.,.,.,.,.,.,.,.,.</li>
        <li>.,.,.,.,.,.,.,.,.,.</li>
        <li>.,.,.,.,.,.,.,.,.,.</li>
        <li>.,.,.,.,.,.,.,.,.,.</li>
        <li>.,.,.,.,.,.,.,.,.,.</li>
        <li>.,.,.,.,.,.,.,.,.,.</li>
      </li>
      <li>
        <li>WoodPlankFloor,WoodPlankFloor,WoodPlankFloor,WoodPlankFloor,WoodPlankFloor,WoodPlankFloor,WoodPlankFloor,WoodPlankFloor,WoodPlankFloor,WoodPlankFloor</li>
        <li>WoodPlankFloor,WoodPlankFloor,WoodPlankFloor,WoodPlankFloor,WoodPlankFloor,WoodPlankFloor,WoodPlankFloor,WoodPlankFloor,WoodPlankFloor,WoodPlankFloor</li>
        <li>WoodPlankFloor,WoodPlankFloor,WoodPlankFloor,WoodPlankFloor,WoodPlankFloor,WoodPlankFloor,WoodPlankFloor,WoodPlankFloor,WoodPlankFloor,WoodPlankFloor</li>
        <li>WoodPlankFloor,WoodPlankFloor,WoodPlankFloor,WoodPlankFloor,WoodPlankFloor,WoodPlankFloor,WoodPlankFloor,WoodPlankFloor,WoodPlankFloor,WoodPlankFloor</li>
        <li>WoodPlankFloor,WoodPlankFloor,WoodPlankFloor,WoodPlankFloor,WoodPlankFloor,WoodPlankFloor,WoodPlankFloor,WoodPlankFloor,WoodPlankFloor,WoodPlankFloor</li>
        <li>WoodPlankFloor,WoodPlankFloor,WoodPlankFloor,WoodPlankFloor,WoodPlankFloor,WoodPlankFloor,WoodPlankFloor,WoodPlankFloor,WoodPlankFloor,WoodPlankFloor</li>
        <li>.,WoodPlankFloor,WoodPlankFloor,WoodPlankFloor,WoodPlankFloor,WoodPlankFloor,WoodPlankFloor,WoodPlankFloor,WoodPlankFloor,WoodPlankFloor</li>
        <li>.,MetalTile,MetalTile,MetalTile,MetalTile,MetalTile,.,.,.,.</li>
        <li>MetalTile,MetalTile,MetalTile,MetalTile,MetalTile,MetalTile,MetalTile,MetalTile,.,.</li>
        <li>MetalTile,MetalTile,MetalTile,MetalTile,MetalTile,MetalTile,MetalTile,MetalTile,.,.</li>
        <li>MetalTile,MetalTile,MetalTile,MetalTile,MetalTile,MetalTile,MetalTile,MetalTile,.,.</li>
        <li>MetalTile,MetalTile,MetalTile,MetalTile,MetalTile,MetalTile,MetalTile,MetalTile,.,.</li>
        <li>MetalTile,MetalTile,MetalTile,MetalTile,MetalTile,MetalTile,MetalTile,MetalTile,.,.</li>
      </li>
      <li>
        <li>Wall_BlocksGranite,Wall_BlocksGranite,Wall_BlocksGranite,Wall_BlocksGranite,Wall_BlocksGranite,Wall_BlocksGranite,Wall_BlocksGranite,Wall_BlocksGranite,Wall_BlocksGranite,Wall_BlocksGranite</li>
        <li>Wall_BlocksGranite,ChessTable_Steel,DiningChair_Steel_West,.,DiningChair_Steel_North,.,DiningChair_Steel_North,DiningChair_Steel_North,StandingLamp,Wall_BlocksGranite</li>
        <li>Wall_BlocksGranite,DiningChair_Steel_South,.,DiningChair_Steel_East,Table1x2c_Steel_East,.,Table1x2c_Steel_East,.,DiningChair_Steel_West,Wall_BlocksGranite</li>
        <li>Wall_BlocksGranite,.,.,.,.,DiningChair_Steel_South,.,DiningChair_Steel_South,.,Wall_BlocksGranite</li>
        <li>Wall_BlocksGranite,.,.,.,.,.,.,.,.,Wall_BlocksGranite</li>
        <li>Wall_BlocksGranite,Wall_BlocksGranite,StandingLamp,.,SculptureLarge_Silver,.,FlatscreenTelevision_South,.,.,Wall_BlocksGranite</li>
        <li>.,Wall_BlocksGranite,Wall_BlocksGranite,Door_Steel,Wall_BlocksGranite,Wall_BlocksGranite,Wall_BlocksGranite,Wall_BlocksGranite,Wall_BlocksGranite,Wall_BlocksGranite</li>
        <li>.,Wall_BlocksGranite,.,.,.,Wall_BlocksGranite,.,.,.,.</li>
        <li>Wall_BlocksGranite,Wall_BlocksGranite,.,.,.,Wall_BlocksGranite,Wall_BlocksGranite,Wall_BlocksGranite,.,.</li>
        <li>Wall_BlocksGranite,.,.,.,.,.,.,Wall_BlocksGranite,.,.</li>
        <li>Wall_BlocksGranite,ElectricStove_West,Stool_Steel_East,StandingLamp,.,Stool_Steel_East,ElectricStove_East,Wall_BlocksGranite,TableButcher_Steel_West,Stool_Steel_East</li>
        <li>Wall_BlocksGranite,.,.,.,.,.,.,Wall_BlocksGranite,.,.</li>
        <li>Wall_BlocksGranite,Wall_BlocksGranite,Wall_BlocksGranite,Wall_BlocksGranite,Wall_BlocksGranite,Door_Steel,Wall_BlocksGranite,Wall_BlocksGranite,.,.</li>
      </li>
    </layouts>
    <roofGrid>
      <li>1,1,1,1,1,1,1,1,1,1</li>
      <li>1,1,1,1,1,1,1,1,1,1</li>
      <li>1,1,1,1,1,1,1,1,1,1</li>
      <li>1,1,1,1,1,1,1,1,1,1</li>
      <li>1,1,1,1,1,1,1,1,1,1</li>
      <li>1,1,1,1,1,1,1,1,1,1</li>
      <li>.,1,1,1,1,1,1,1,1,1</li>
      <li>.,1,1,1,1,1,.,.,.,.</li>
      <li>1,1,1,1,1,1,1,1,.,.</li>
      <li>1,1,1,1,1,1,1,1,.,.</li>
      <li>1,1,1,1,1,1,1,1,.,.</li>
      <li>1,1,1,1,1,1,1,1,.,.</li>
      <li>1,1,1,1,1,1,1,1,.,.</li>
    </roofGrid>
    <tags>
      <li>GenericKitchen</li>
    </tags>
  </KCSG.StructureLayoutDef>
  <KCSG.StructureLayoutDef>
    <defName>VFES_KitchenAndStock</defName>
    <layouts>
      <li>
        <li>.,.,.,.,.,.,.,.,.,.,.,.,.</li>
        <li>.,.,RawRice,.,.,.,.,.,.,RawRice,.,.,.</li>
        <li>.,.,.,.,RawRice,RawCorn,.,.,.,.,RawCorn,.,.</li>
        <li>.,.,.,.,.,.,RawCorn,RawRice,.,.,.,.,.</li>
        <li>.,.,RawRice,RawCorn,.,.,.,.,.,RawRice,.,.,.</li>
        <li>.,.,.,.,RawCorn,.,RawRice,.,.,.,RawCorn,.,.</li>
        <li>.,.,.,.,.,.,.,.,.,.,.,.,.</li>
        <li>.,.,.,.,.,.,.,.,.,.,.,.,.</li>
        <li>.,.,.,.,.,.,.,.,.,.,.,.,.</li>
        <li>.,.,.,.,.,.,.,.,.,.,.,.,.</li>
        <li>.,.,.,.,.,.,.,.,.,.,.,.,.</li>
        <li>.,.,.,.,.,.,.,.,.,.,.,.,.</li>
      </li>
      <li>
        <li>.,.,.,.,.,.,.,.,.,.,.,.,.</li>
        <li>.,SterileTile,SterileTile,SterileTile,SterileTile,SterileTile,SterileTile,SterileTile,SterileTile,SterileTile,SterileTile,SterileTile,.</li>
        <li>.,SterileTile,SterileTile,SterileTile,SterileTile,SterileTile,SterileTile,SterileTile,SterileTile,SterileTile,SterileTile,SterileTile,.</li>
        <li>SterileTile,SterileTile,SterileTile,SterileTile,SterileTile,SterileTile,SterileTile,SterileTile,SterileTile,SterileTile,SterileTile,SterileTile,SterileTile</li>
        <li>.,SterileTile,SterileTile,SterileTile,SterileTile,SterileTile,SterileTile,SterileTile,SterileTile,SterileTile,SterileTile,SterileTile,.</li>
        <li>.,SterileTile,SterileTile,SterileTile,SterileTile,SterileTile,SterileTile,SterileTile,SterileTile,SterileTile,SterileTile,SterileTile,.</li>
        <li>.,.,.,.,MetalTile,.,.,.,.,.,MetalTile,.,.</li>
        <li>.,MetalTile,MetalTile,MetalTile,MetalTile,MetalTile,MetalTile,MetalTile,.,MetalTile,MetalTile,MetalTile,.</li>
        <li>.,MetalTile,MetalTile,MetalTile,MetalTile,MetalTile,MetalTile,MetalTile,.,MetalTile,MetalTile,MetalTile,.</li>
        <li>.,MetalTile,MetalTile,MetalTile,MetalTile,MetalTile,MetalTile,MetalTile,.,MetalTile,MetalTile,MetalTile,.</li>
        <li>.,.,.,.,.,.,.,.,.,.,MetalTile,.,.</li>
        <li>.,.,.,.,.,.,.,.,.,.,.,.,.</li>
      </li>
      <li>
        <li>Wall_WoodLog,Wall_WoodLog,Wall_WoodLog,Wall_WoodLog,Wall_WoodLog,Cooler_South,Wall_WoodLog,Cooler_South,Wall_WoodLog,Wall_WoodLog,Wall_WoodLog,Wall_WoodLog,Wall_WoodLog</li>
        <li>Wall_WoodLog,.,.,.,.,.,.,.,.,.,.,.,Wall_WoodLog</li>
        <li>Wall_WoodLog,.,.,.,.,.,.,.,.,.,.,.,Wall_WoodLog</li>
        <li>Autodoor_WoodLog,.,.,.,.,.,.,.,.,.,.,.,Autodoor_WoodLog</li>
        <li>Wall_WoodLog,.,.,.,.,.,.,.,.,.,.,.,Wall_WoodLog</li>
        <li>Wall_WoodLog,.,.,.,.,.,.,.,.,.,.,.,Wall_WoodLog</li>
        <li>Wall_WoodLog,Wall_WoodLog,Wall_WoodLog,Wall_WoodLog,Autodoor_WoodLog,Wall_WoodLog,Wall_WoodLog,Wall_WoodLog,Wall_WoodLog,Wall_WoodLog,Autodoor_WoodLog,Wall_WoodLog,Wall_WoodLog</li>
        <li>Wall_WoodLog,.,.,.,.,.,.,.,Wall_WoodLog,.,.,.,Wall_WoodLog</li>
        <li>Wall_WoodLog,.,DiningChair_WoodLog_North,.,.,.,DiningChair_WoodLog_North,.,Wall_WoodLog,.,DiningChair_WoodLog_North,.,Wall_WoodLog</li>
        <li>Wall_WoodLog,.,ElectricStove_North,.,StandingLamp,.,ElectricStove_North,.,Wall_WoodLog,.,TableButcher_WoodLog_North,.,Wall_WoodLog</li>
        <li>Wall_WoodLog,Wall_WoodLog,Wall_WoodLog,Wall_WoodLog,Wall_WoodLog,Wall_WoodLog,Wall_WoodLog,Wall_WoodLog,Wall_WoodLog,Wall_WoodLog,StandingLamp,Wall_WoodLog,Wall_WoodLog</li>
        <li>.,.,.,.,.,.,.,.,.,Wall_WoodLog,Wall_WoodLog,Wall_WoodLog,.</li>
      </li>
    </layouts>
    <roofGrid>
      <li>1,1,1,1,1,1,1,1,1,1,1,1,1</li>
      <li>1,1,1,1,1,1,1,1,1,1,1,1,1</li>
      <li>1,1,1,1,1,1,1,1,1,1,1,1,1</li>
      <li>1,1,1,1,1,1,1,1,1,1,1,1,1</li>
      <li>1,1,1,1,1,1,1,1,1,1,1,1,1</li>
      <li>1,1,1,1,1,1,1,1,1,1,1,1,1</li>
      <li>1,1,1,1,1,1,1,1,1,1,1,1,1</li>
      <li>1,1,1,1,1,1,1,1,1,1,1,1,1</li>
      <li>1,1,1,1,1,1,1,1,1,1,1,1,1</li>
      <li>1,1,1,1,1,1,1,1,1,1,1,1,1</li>
      <li>1,1,1,1,1,1,1,1,1,1,1,1,1</li>
      <li>.,.,.,.,.,.,.,.,.,1,1,1,.</li>
    </roofGrid>
    <tags>
      <li>GenericKitchen</li>
    </tags>
  </KCSG.StructureLayoutDef>
  <KCSG.StructureLayoutDef>
    <defName>VFES_KitchenAndStock2</defName>
    <layouts>
      <li>
        <li>.,.,.,.,.,.,.,.,.,.</li>
        <li>.,.,.,.,.,.,.,.,.,.</li>
        <li>.,.,.,.,.,.,.,.,.,.</li>
        <li>.,.,.,.,.,.,.,.,.,.</li>
        <li>.,.,.,.,.,.,.,.,.,.</li>
        <li>.,.,.,.,.,.,.,.,.,.</li>
        <li>.,.,.,.,.,.,.,.,.,.</li>
        <li>.,.,.,.,.,.,.,.,.,.</li>
        <li>.,.,RawPotatoes,RawPotatoes,.,.,.,.,.,.</li>
        <li>.,.,.,.,.,.,.,MealSurvivalPack,.,.</li>
        <li>.,.,.,Meat_Wolf_Timber,Meat_Wolf_Timber,MealSurvivalPack,.,Meat_Wolf_Timber,.,.</li>
        <li>.,Meat_Wolf_Timber,.,MealSurvivalPack,Meat_Wolf_Timber,Meat_Wolf_Timber,.,Meat_Wolf_Timber,.,.</li>
        <li>.,Meat_Wolf_Timber,.,.,.,.,.,Meat_Wolf_Timber,.,.</li>
        <li>.,MealSurvivalPack,Meat_Wolf_Timber,Meat_Wolf_Timber,Meat_Wolf_Timber,RawPotatoes,MealSurvivalPack,.,.,.</li>
        <li>.,.,.,.,.,.,.,.,.,.</li>
      </li>
      <li>
        <li>.,.,.,.,.,.,.,.,.,.</li>
        <li>.,WoodPlankFloor,WoodPlankFloor,WoodPlankFloor,WoodPlankFloor,WoodPlankFloor,WoodPlankFloor,.,.,.</li>
        <li>.,.,WoodPlankFloor,WoodPlankFloor,WoodPlankFloor,WoodPlankFloor,WoodPlankFloor,WoodPlankFloor,.,.</li>
        <li>.,WoodPlankFloor,WoodPlankFloor,WoodPlankFloor,WoodPlankFloor,WoodPlankFloor,WoodPlankFloor,WoodPlankFloor,.,.</li>
        <li>.,.,WoodPlankFloor,WoodPlankFloor,WoodPlankFloor,WoodPlankFloor,WoodPlankFloor,WoodPlankFloor,.,.</li>
        <li>.,WoodPlankFloor,WoodPlankFloor,WoodPlankFloor,WoodPlankFloor,WoodPlankFloor,WoodPlankFloor,WoodPlankFloor,WoodPlankFloor,.</li>
        <li>.,WoodPlankFloor,WoodPlankFloor,WoodPlankFloor,WoodPlankFloor,WoodPlankFloor,WoodPlankFloor,WoodPlankFloor,WoodPlankFloor,.</li>
        <li>.,.,.,.,.,.,WoodPlankFloor,WoodPlankFloor,WoodPlankFloor,.</li>
        <li>.,.,.,.,.,.,.,.,.,.</li>
        <li>.,.,.,.,.,.,.,.,.,.</li>
        <li>.,.,.,.,.,.,.,.,.,.</li>
        <li>.,.,.,.,.,.,.,.,.,.</li>
        <li>.,.,.,.,.,.,.,.,.,.</li>
        <li>.,.,.,.,.,.,.,.,.,.</li>
        <li>.,.,.,.,.,.,.,.,.,.</li>
      </li>
      <li>
        <li>.,Wall_BlocksGranite,Wall_BlocksGranite,Wall_BlocksGranite,Wall_BlocksGranite,Wall_BlocksGranite,Wall_BlocksGranite,Wall_BlocksGranite,.,.</li>
        <li>.,Door_BlocksGranite,.,.,.,TableButcher_WoodLog_South,.,Wall_BlocksGranite,Wall_BlocksGranite,.</li>
        <li>.,Wall_BlocksGranite,.,.,.,DiningChair_WoodLog_South,.,.,Wall_BlocksGranite,.</li>
        <li>.,Door_BlocksGranite,.,.,.,.,.,.,.,.</li>
        <li>Wall_BlocksGranite,Wall_BlocksGranite,.,.,.,.,.,.,Wall_BlocksGranite,Wall_BlocksGranite</li>
        <li>Wall_BlocksGranite,Table1x2c_WoodLog_North,Stool_WoodLog_East,.,.,.,.,.,.,Wall_BlocksGranite</li>
        <li>Wall_BlocksGranite,.,Stool_WoodLog_East,.,.,StandingLamp,.,DiningChair_WoodLog_North,.,Wall_BlocksGranite</li>
        <li>Wall_BlocksGranite,Wall_BlocksGranite,Wall_BlocksGranite,Wall_BlocksGranite,Door_BlocksGranite,Wall_BlocksGranite,.,ElectricStove_North,.,Wall_BlocksGranite</li>
        <li>.,Wall_BlocksGranite,Shelf_WoodLog_North,.,.,Wall_BlocksGranite,Wall_BlocksGranite,Wall_BlocksGranite,Wall_BlocksGranite,Wall_BlocksGranite</li>
        <li>.,Wall_BlocksGranite,.,.,.,.,.,Shelf_WoodLog_West,Wall_BlocksGranite,.</li>
        <li>Wall_BlocksGranite,Wall_BlocksGranite,.,Shelf_WoodLog_West,.,Shelf_WoodLog_South,.,.,Cooler_East,.</li>
        <li>Wall_BlocksGranite,.,.,.,Shelf_WoodLog_North,.,.,Shelf_WoodLog_West,Wall_BlocksGranite,.</li>
        <li>Wall_BlocksGranite,Shelf_WoodLog_East,.,.,.,.,.,.,Cooler_East,.</li>
        <li>Wall_BlocksGranite,.,Shelf_WoodLog_South,.,Shelf_WoodLog_South,.,Shelf_WoodLog_South,Wall_BlocksGranite,Wall_BlocksGranite,.</li>
        <li>Wall_BlocksGranite,Wall_BlocksGranite,Wall_BlocksGranite,Wall_BlocksGranite,Wall_BlocksGranite,Wall_BlocksGranite,Wall_BlocksGranite,Wall_BlocksGranite,.,.</li>
      </li>
      <li>
        <li>.,.,.,.,.,.,.,.,.,.</li>
        <li>.,.,.,.,.,.,.,.,.,.</li>
        <li>.,.,.,.,.,.,.,.,.,.</li>
        <li>.,.,.,.,.,.,.,.,Door_BlocksGranite,.</li>
        <li>.,.,.,.,.,.,.,.,.,.</li>
        <li>.,.,.,.,.,.,.,.,.,.</li>
        <li>.,.,.,.,.,.,.,.,.,.</li>
        <li>.,.,.,.,.,.,.,.,.,.</li>
        <li>.,.,.,.,.,.,.,.,.,.</li>
        <li>.,.,.,.,.,.,.,.,.,.</li>
        <li>.,.,.,.,.,.,.,.,.,.</li>
        <li>.,.,.,.,.,.,.,.,.,.</li>
        <li>.,.,.,.,.,.,.,.,.,.</li>
        <li>.,.,.,.,.,.,.,.,.,.</li>
        <li>.,.,.,.,.,.,.,.,.,.</li>
      </li>
    </layouts>
    <roofGrid>
      <li>.,1,1,1,.,.,.,.,.,.</li>
      <li>.,1,1,1,1,1,1,1,.,.</li>
      <li>.,1,1,1,1,1,1,1,.,.</li>
      <li>.,1,1,1,1,1,1,1,.,.</li>
      <li>.,1,1,1,1,1,1,1,.,.</li>
      <li>.,1,1,1,1,1,1,1,1,.</li>
      <li>.,1,1,1,1,1,1,1,1,.</li>
      <li>.,.,1,1,1,1,1,1,1,.</li>
      <li>.,.,1,1,1,1,1,1,.,.</li>
      <li>.,.,1,1,1,1,1,1,.,.</li>
      <li>.,.,1,1,1,1,1,1,.,.</li>
      <li>.,1,1,1,1,1,1,1,.,.</li>
      <li>.,1,1,1,1,1,1,1,.,.</li>
      <li>.,1,1,1,1,1,1,.,.,.</li>
      <li>.,.,.,.,.,.,.,.,.,.</li>
    </roofGrid>
    <tags>
      <li>GenericKitchen</li>
    </tags>
  </KCSG.StructureLayoutDef>
</Defs>